thallu/__init__.py
thallu/git_thallu.py
thallu-0.1.7.dist-info/licenses/LICENCE
thallu-0.1.7.dist-info/METADATA
thallu-0.1.7.dist-info/WHEEL
thallu-0.1.7.dist-info/entry_points.txt
thallu-0.1.7.dist-info/top_level.txt
thallu-0.1.7.dist-info/RECORD
