Metadata-Version: 2.4
Name: thallu
Version: 0.1.7
Summary: Lightweight CLI to streamline Git workflows
Home-page: https://github.com/Naveensivam03/thallu
Author: Naveensivam03
Classifier: Programming Language :: Python :: 3
Classifier: Operating System :: OS Independent
Classifier: Intended Audience :: Developers
Classifier: License :: OSI Approved :: MIT License
Classifier: Topic :: Software Development :: Version Control :: Git
Requires-Python: >=3.7
License-File: LICENCE
Requires-Dist: inquirer>=3.4.0
Requires-Dist: questionary>=2.1.0
Dynamic: author
Dynamic: classifier
Dynamic: description
Dynamic: description-content-type
Dynamic: home-page
Dynamic: license-file
Dynamic: requires-dist
Dynamic: requires-python
Dynamic: summary
